modelbricks/__init__.py
modelbricks/layers/__init__.py
modelbricks/layers/layers.py
modelbricks/metrics/__init__.py
modelbricks/metrics/metrics.py
modelbricks/models/__init__.py
modelbricks/models/models.py
modelbricks-0.1.3.dist-info/LICENSE
modelbricks-0.1.3.dist-info/METADATA
modelbricks-0.1.3.dist-info/WHEEL
modelbricks-0.1.3.dist-info/top_level.txt
modelbricks-0.1.3.dist-info/RECORD
